ZnProject/__init__.py
ZnProject/operation.py
ZnProject-0.0.4.dist-info/METADATA
ZnProject-0.0.4.dist-info/WHEEL
ZnProject-0.0.4.dist-info/top_level.txt
ZnProject-0.0.4.dist-info/zip-safe
ZnProject-0.0.4.dist-info/RECORD
